abdpymc/__init__.py
abdpymc/abd.py
abdpymc/plotting.py
abdpymc/simulation.py
abdpymc/subsample_idata.py
abdpymc/survival.py
abdpymc/test_abd.py
abdpymc/test_plotting.py
abdpymc/test_simulation.py
abdpymc/test_survival.py
abdpymc/timelines.py
abdpymc-1.0.5.dist-info/licenses/LICENSE.txt
data/cohort_data/df.csv
data/cohort_data/ititers.csv
data/cohort_data/pcrpos.txt
data/cohort_data/t0.txt
data/cohort_data/vacs.txt
data/inference_data/abd-20231202-256.nc
data/test_data/cohort_data/df.csv
data/test_data/cohort_data/pcrpos.txt
data/test_data/cohort_data/t0.txt
data/test_data/cohort_data/vacs.txt
hooks/pre-commit
abdpymc-1.0.5.dist-info/METADATA
abdpymc-1.0.5.dist-info/WHEEL
abdpymc-1.0.5.dist-info/entry_points.txt
abdpymc-1.0.5.dist-info/top_level.txt
abdpymc-1.0.5.dist-info/RECORD
