Metadata-Version: 2.4
Name: abdpymc
Version: 1.0.5
Summary: Antibody dynamics using PyMC
Author-email: David Pattinson <david.pattinson@wisc.edu>
License:                     GNU GENERAL PUBLIC LICENSE
Project-URL: Repository, https://github.com/davipatti/abdpymc
Keywords: pymc,antibody dynamics,sars-cov-2,influenza,antibody,titer,bayesian inference
Classifier: Development Status :: 3 - Alpha
Classifier: Programming Language :: Python
Requires-Python: >=3.8
License-File: LICENSE.txt
Requires-Dist: arviz
Requires-Dist: matplotlib
Requires-Dist: numpy
Requires-Dist: pandas
Requires-Dist: pydantic
Requires-Dist: pymc
Provides-Extra: dev
Requires-Dist: pytest; extra == "dev"
Requires-Dist: flake8; extra == "dev"
Dynamic: license-file
